LICENSE
MANIFEST.in
readme.md
setup.py
sysutils.py
sysutils.egg-info/PKG-INFO
sysutils.egg-info/SOURCES.txt
sysutils.egg-info/dependency_links.txt
sysutils.egg-info/requires.txt
sysutils.egg-info/top_level.txt