Metadata-Version: 1.0
Name: sysutils
Version: 0.0.2
Summary: Simple helpers for systems managements
Home-page: https://github.com/obsoleter/sysutils
Author: Jeremy Axmacher
Author-email: jeremy@obsoleter.com
License: Copyright (C) 2012 Jeremy Axmacher
